tencentcloud/__init__.py
tencentcloud/thpc/__init__.py
tencentcloud/thpc/v20211109/__init__.py
tencentcloud/thpc/v20211109/errorcodes.py
tencentcloud/thpc/v20211109/models.py
tencentcloud/thpc/v20211109/thpc_client.py
tencentcloud/thpc/v20211109/thpc_client_async.py
tencentcloud/thpc/v20220401/__init__.py
tencentcloud/thpc/v20220401/errorcodes.py
tencentcloud/thpc/v20220401/models.py
tencentcloud/thpc/v20220401/thpc_client.py
tencentcloud/thpc/v20220401/thpc_client_async.py
tencentcloud/thpc/v20230321/__init__.py
tencentcloud/thpc/v20230321/errorcodes.py
tencentcloud/thpc/v20230321/models.py
tencentcloud/thpc/v20230321/thpc_client.py
tencentcloud/thpc/v20230321/thpc_client_async.py
tencentcloud_sdk_python_thpc-3.1.17.dist-info/METADATA
tencentcloud_sdk_python_thpc-3.1.17.dist-info/WHEEL
tencentcloud_sdk_python_thpc-3.1.17.dist-info/top_level.txt
tencentcloud_sdk_python_thpc-3.1.17.dist-info/RECORD
